[
  {
    "ref": "1:1",
    "surah": 1,
    "ayah": 1,
    "arabic": "بِسۡمِ ٱللَّهِ ٱلرَّحۡمَٰنِ ٱلرَّحِيمِ",
    "english": "In the name of Allah, the Entirely Merciful, the Especially Merciful"
  },
  {
    "ref": "1:2",
    "surah": 1,
    "ayah": 2,
    "arabic": "ٱلۡحَمۡدُ لِلَّهِ رَبِّ ٱلۡعَٰلَمِينَ",
    "english": "[All] praise is [due] to Allah, Lord of the worlds"
  },
  {
    "ref": "1:3",
    "surah": 1,
    "ayah": 3,
    "arabic": "ٱلرَّحۡمَٰنِ ٱلرَّحِيمِ",
    "english": "The Entirely Merciful, the Especially Merciful"
  },
  {
    "ref": "1:4",
    "surah": 1,
    "ayah": 4,
    "arabic": "مَٰلِكِ يَوۡمِ ٱلدِّينِ",
    "english": "Sovereign of the Day of Recompense"
  },
  {
    "ref": "1:5",
    "surah": 1,
    "ayah": 5,
    "arabic": "إِيَّاكَ نَعۡبُدُ وَإِيَّاكَ نَسۡتَعِينُ",
    "english": "It is You we worship and You we ask for help"
  },
  {
    "ref": "1:6",
    "surah": 1,
    "ayah": 6,
    "arabic": "ٱهۡدِنَا ٱلصِّرَٰطَ ٱلۡمُسۡتَقِيمَ",
    "english": "Guide us to the straight path"
  },
  {
    "ref": "1:7",
    "surah": 1,
    "ayah": 7,
    "arabic": "صِرَٰطَ ٱلَّذِينَ أَنۡعَمۡتَ عَلَيۡهِمۡ غَيۡرِ ٱلۡمَغۡضُوبِ عَلَيۡهِمۡ وَلَا ٱلضَّآلِّينَ",
    "english": "The path of those upon whom You have bestowed favor, not of those who have evoked [Your] anger or of those who are astray"
  }
]